uCipher/__init__.py
uCipher/main.py
encryptext-6.2.dist-info/METADATA
encryptext-6.2.dist-info/WHEEL
encryptext-6.2.dist-info/top_level.txt
encryptext-6.2.dist-info/RECORD
