Metadata-Version: 2.4
Name: encryptext
Version: 6.2
Author: YusufA442
Author-email: yusuf365820@gmail.com
License: Creative Commons Attribution-Noncommercial-Share Alike license
Requires-Dist: LibraryBasics
Dynamic: author
Dynamic: author-email
Dynamic: description
Dynamic: license
Dynamic: requires-dist
